pytsterrors/__init__.py
pytsterrors/__init__.pyi
pytsterrors/exception.py
pytsterrors/exception.pyi
pytsterrors/utils.py
pytsterrors/utils.pyi
pytsterrors-0.4.1.dist-info/METADATA
pytsterrors-0.4.1.dist-info/WHEEL
pytsterrors-0.4.1.dist-info/licenses/LICENSE
pytsterrors-0.4.1.dist-info/RECORD
