Metadata-Version: 2.4
Name: pytsterrors
Version: 0.4.1
Summary: pytsterrors contains an exception that helps to validate trace calls
License: MIT
License-File: LICENSE
Author: Manos Ragiadakos
Requires-Python: >=3.11
Classifier: License :: OSI Approved :: MIT License
Classifier: Programming Language :: Python :: 3
Classifier: Programming Language :: Python :: 3.11
Classifier: Programming Language :: Python :: 3.12
Classifier: Programming Language :: Python :: 3.13
Classifier: Programming Language :: Python :: 3.14
